README.md
setup.py
dl_hello_world.egg-info/PKG-INFO
dl_hello_world.egg-info/SOURCES.txt
dl_hello_world.egg-info/dependency_links.txt
dl_hello_world.egg-info/top_level.txt
sample_package/__init__.py
sample_package/sample.py